mahesh_bpe/BPE.py
mahesh_bpe/__init__.py
mahesh_bpe-0.1.0.dist-info/METADATA
mahesh_bpe-0.1.0.dist-info/WHEEL
mahesh_bpe-0.1.0.dist-info/top_level.txt
mahesh_bpe-0.1.0.dist-info/RECORD
