Metadata-Version: 2.4
Name: mahesh-bpe
Version: 0.1.0
Summary: Mahesh's Byte Pair Encoding tokenizer
Author: Durja LLC, Manoj Nayak
Author-email: Manoj Nayak <manojvnayak@outlook.in>
Maintainer: Manoj Nayak
Maintainer-email: manojvnayak@outlook.in
License: MIT
Requires-Python: >=3.7
Requires-Dist: numpy
Dynamic: author
Dynamic: maintainer
Dynamic: maintainer-email
Dynamic: requires-python
